{
  "resource": "cities",
  "http_method": "GET",
  "route": "/cities",
  "description": "get all cities",
  "explanation": null,
  "parameters": [
    {
      "name": "active",
      "description": "1/0 get cities marked as active"
    }
  ],
  "response_fields": [

  ],
  "requests": [
    {
      "request_method": "GET",
      "request_path": "/cities?active=1",
      "request_body": null,
      "request_headers": {
        "Host": "example.org",
        "Cookie": ""
      },
      "request_query_parameters": {
        "active": "1"
      },
      "request_content_type": null,
      "response_status": 200,
      "response_status_text": "OK",
      "response_body": "[\n  {\n    \"id\": 1,\n    \"name\": \"Karimnagar\",\n    \"active\": true\n  },\n  {\n    \"id\": 2,\n    \"name\": \"Parbhani\",\n    \"active\": true\n  },\n  {\n    \"id\": 3,\n    \"name\": \"Etawah\",\n    \"active\": true\n  },\n  {\n    \"id\": 6,\n    \"name\": \"New Delhi\",\n    \"active\": true\n  },\n  {\n    \"id\": 7,\n    \"name\": \"Chhapra\",\n    \"active\": true\n  },\n  {\n    \"id\": 8,\n    \"name\": \"Kadapa\",\n    \"active\": true\n  },\n  {\n    \"id\": 9,\n    \"name\": \"Ramagundam\",\n    \"active\": true\n  }\n]",
      "response_headers": {
        "X-Frame-Options": "SAMEORIGIN",
        "X-XSS-Protection": "1; mode=block",
        "X-Content-Type-Options": "nosniff",
        "Content-Type": "application/json; charset=utf-8",
        "ETag": "W/\"92c5457c8a591369cec7b48dfc5a2b33\"",
        "Cache-Control": "max-age=0, private, must-revalidate",
        "X-Request-Id": "0e315509-253a-45f9-9e72-e026a1e080c2",
        "X-Runtime": "0.025916",
        "Content-Length": "288"
      },
      "response_content_type": "application/json; charset=utf-8",
      "curl": "curl \"http://localhost:3000/cities?active=1\" -X GET \\\n\t-H \"Host: example.org\" \\\n\t-H \"Cookie: \""
    }
  ]
}