{
  "resource": "client: users",
  "http_method": "POST",
  "route": "/auth",
  "description": "create user: invalid params",
  "explanation": null,
  "parameters": [
    {
      "required": true,
      "name": "phone",
      "description": " phone"
    },
    {
      "required": true,
      "name": "email",
      "description": " email"
    },
    {
      "required": true,
      "name": "password",
      "description": " password"
    },
    {
      "required": true,
      "name": "password_confirmation",
      "description": " password confirmation"
    },
    {
      "required": true,
      "name": "first_name",
      "description": " first name"
    },
    {
      "required": true,
      "name": "last_name",
      "description": " last name"
    },
    {
      "name": "how_did_you_hear_about_us",
      "description": " how did you hear about us"
    }
  ],
  "response_fields": [

  ],
  "requests": [
    {
      "request_method": "POST",
      "request_path": "/auth",
      "request_body": "email=165titus%40millerstark.co&password=secrety_bickety&password_confirmation=secrety_bickety&first_name=Mattie&last_name=Ruecker&phone",
      "request_headers": {
        "Access-Token": "2UX17oCU05K-Z-lLybLYzQ",
        "Token-Type": "Bearer",
        "Client": "NIpHTVa0jFv-AYqrp3lqEQ",
        "Expiry": "1459372674",
        "Uid": "166danial@schulist.info",
        "Host": "example.org",
        "Content-Type": "application/x-www-form-urlencoded",
        "Cookie": ""
      },
      "request_query_parameters": {
      },
      "request_content_type": "application/x-www-form-urlencoded",
      "response_status": 403,
      "response_status_text": "Forbidden",
      "response_body": "{\n  \"status\": \"error\",\n  \"data\": {\n    \"id\": null,\n    \"first_name\": \"Mattie\",\n    \"last_name\": \"Ruecker\",\n    \"email\": \"165titus@millerstark.co\",\n    \"provider\": \"email\",\n    \"uid\": \"\",\n    \"phone\": null,\n    \"verification_code\": null,\n    \"is_verified\": false,\n    \"created_at\": null,\n    \"updated_at\": null,\n    \"how_did_you_hear_about_us\": null\n  },\n  \"errors\": {\n    \"phone\": [\n      \"is not a number\",\n      \"is the wrong length (should be 10 characters)\",\n      \"can't be blank\"\n    ],\n    \"full_messages\": [\n      \"Phone is not a number\",\n      \"Phone is the wrong length (should be 10 characters)\",\n      \"Phone can't be blank\"\n    ]\n  }\n}",
      "response_headers": {
        "X-Frame-Options": "SAMEORIGIN",
        "X-XSS-Protection": "1; mode=block",
        "X-Content-Type-Options": "nosniff",
        "Content-Type": "application/json; charset=utf-8",
        "Cache-Control": "no-cache",
        "X-Request-Id": "34d1a529-9422-48fe-8bc8-458dc89c81fe",
        "X-Runtime": "0.009319",
        "Content-Length": "493"
      },
      "response_content_type": "application/json; charset=utf-8",
      "curl": "curl \"http://localhost:3000/auth\" -d 'email=165titus%40millerstark.co&password=secrety_bickety&password_confirmation=secrety_bickety&first_name=Mattie&last_name=Ruecker&phone' -X POST \\\n\t-H \"Access-Token: 2UX17oCU05K-Z-lLybLYzQ\" \\\n\t-H \"Token-Type: Bearer\" \\\n\t-H \"Client: NIpHTVa0jFv-AYqrp3lqEQ\" \\\n\t-H \"Expiry: 1459372674\" \\\n\t-H \"Uid: 166danial@schulist.info\" \\\n\t-H \"Host: example.org\" \\\n\t-H \"Content-Type: application/x-www-form-urlencoded\" \\\n\t-H \"Cookie: \""
    }
  ]
}