{
  "resource": "products",
  "http_method": "GET",
  "route": "/products/:id",
  "description": "get product",
  "explanation": null,
  "parameters": [

  ],
  "response_fields": [

  ],
  "requests": [
    {
      "request_method": "GET",
      "request_path": "/products/22",
      "request_body": null,
      "request_headers": {
        "Host": "example.org",
        "Cookie": ""
      },
      "request_query_parameters": {
      },
      "request_content_type": null,
      "response_status": 200,
      "response_status_text": "OK",
      "response_body": "{\n  \"id\": 22,\n  \"city_id\": 16,\n  \"title\": \"fish\",\n  \"price\": \"3.0\",\n  \"description\": null,\n  \"created_at\": \"2016-03-18T11:16:00.787Z\",\n  \"updated_at\": \"2016-03-18T11:16:00.787Z\",\n  \"inventory_count\": 20,\n  \"image_url\": \"https://freshrocket-test.s3.amazonaws.com/uploads/product/image/default.png\"\n}",
      "response_headers": {
        "X-Frame-Options": "SAMEORIGIN",
        "X-XSS-Protection": "1; mode=block",
        "X-Content-Type-Options": "nosniff",
        "Content-Type": "application/json; charset=utf-8",
        "ETag": "W/\"69ca861d1c2ade67ea1b0199006af863\"",
        "Cache-Control": "max-age=0, private, must-revalidate",
        "X-Request-Id": "ac99cd5c-ddef-4e8f-866b-70c28237f4c9",
        "X-Runtime": "0.002213",
        "Content-Length": "261"
      },
      "response_content_type": "application/json; charset=utf-8",
      "curl": "curl \"http://localhost:3000/products/22\" -X GET \\\n\t-H \"Host: example.org\" \\\n\t-H \"Cookie: \""
    }
  ]
}