{
  "resource": "products",
  "http_method": "GET",
  "route": "/products",
  "description": "get all products",
  "explanation": "returns all products with no params",
  "parameters": [
    {
      "name": "city_id",
      "description": " city"
    },
    {
      "name": "category_id",
      "description": " category"
    },
    {
      "name": "in_stock",
      "description": "1/0, if absent will return all"
    }
  ],
  "response_fields": [

  ],
  "requests": [
    {
      "request_method": "GET",
      "request_path": "/products",
      "request_body": null,
      "request_headers": {
        "Host": "example.org",
        "Cookie": ""
      },
      "request_query_parameters": {
      },
      "request_content_type": null,
      "response_status": 200,
      "response_status_text": "OK",
      "response_body": "[\n  {\n    \"id\": 1,\n    \"city_id\": 1,\n    \"title\": \"fish\",\n    \"price\": \"3.0\",\n    \"description\": null,\n    \"created_at\": \"2016-03-12T04:25:45.018Z\",\n    \"updated_at\": \"2016-03-12T04:25:45.908Z\",\n    \"inventory_count\": 20,\n    \"image_url\": \"uploads/product/image/default.png\"\n  },\n  {\n    \"id\": 2,\n    \"city_id\": 1,\n    \"title\": \"fish\",\n    \"price\": \"3.0\",\n    \"description\": null,\n    \"created_at\": \"2016-03-12T04:25:45.353Z\",\n    \"updated_at\": \"2016-03-12T04:25:46.019Z\",\n    \"inventory_count\": 20,\n    \"image_url\": \"uploads/product/image/default.png\"\n  },\n  {\n    \"id\": 3,\n    \"city_id\": 1,\n    \"title\": \"fish\",\n    \"price\": \"3.0\",\n    \"description\": null,\n    \"created_at\": \"2016-03-12T04:25:45.685Z\",\n    \"updated_at\": \"2016-03-12T04:25:46.130Z\",\n    \"inventory_count\": 20,\n    \"image_url\": \"uploads/product/image/default.png\"\n  },\n  {\n    \"id\": 4,\n    \"city_id\": 5,\n    \"title\": \"fish\",\n    \"price\": \"3.0\",\n    \"description\": null,\n    \"created_at\": \"2016-03-12T04:25:47.009Z\",\n    \"updated_at\": \"2016-03-12T04:25:48.085Z\",\n    \"inventory_count\": 20,\n    \"image_url\": \"uploads/product/image/default.png\"\n  },\n  {\n    \"id\": 5,\n    \"city_id\": 5,\n    \"title\": \"fish\",\n    \"price\": \"3.0\",\n    \"description\": null,\n    \"created_at\": \"2016-03-12T04:25:47.407Z\",\n    \"updated_at\": \"2016-03-12T04:25:48.219Z\",\n    \"inventory_count\": 20,\n    \"image_url\": \"uploads/product/image/default.png\"\n  },\n  {\n    \"id\": 6,\n    \"city_id\": 5,\n    \"title\": \"fish\",\n    \"price\": \"3.0\",\n    \"description\": null,\n    \"created_at\": \"2016-03-12T04:25:47.818Z\",\n    \"updated_at\": \"2016-03-12T04:25:48.352Z\",\n    \"inventory_count\": 20,\n    \"image_url\": \"uploads/product/image/default.png\"\n  },\n  {\n    \"id\": 7,\n    \"city_id\": 9,\n    \"title\": \"fish\",\n    \"price\": \"3.0\",\n    \"description\": null,\n    \"created_at\": \"2016-03-12T04:25:55.309Z\",\n    \"updated_at\": \"2016-03-12T04:25:55.309Z\",\n    \"inventory_count\": 20,\n    \"image_url\": \"uploads/product/image/default.png\"\n  },\n  {\n    \"id\": 8,\n    \"city_id\": 9,\n    \"title\": \"fish\",\n    \"price\": \"3.0\",\n    \"description\": null,\n    \"created_at\": \"2016-03-12T04:25:55.420Z\",\n    \"updated_at\": \"2016-03-12T04:25:55.420Z\",\n    \"inventory_count\": 20,\n    \"image_url\": \"uploads/product/image/default.png\"\n  },\n  {\n    \"id\": 9,\n    \"city_id\": 9,\n    \"title\": \"fish\",\n    \"price\": \"3.0\",\n    \"description\": null,\n    \"created_at\": \"2016-03-12T04:25:55.532Z\",\n    \"updated_at\": \"2016-03-12T04:25:55.532Z\",\n    \"inventory_count\": 20,\n    \"image_url\": \"uploads/product/image/default.png\"\n  },\n  {\n    \"id\": 10,\n    \"city_id\": 9,\n    \"title\": \"fish\",\n    \"price\": \"3.0\",\n    \"description\": null,\n    \"created_at\": \"2016-03-12T04:25:55.645Z\",\n    \"updated_at\": \"2016-03-12T04:25:55.645Z\",\n    \"inventory_count\": 20,\n    \"image_url\": \"uploads/product/image/default.png\"\n  },\n  {\n    \"id\": 11,\n    \"city_id\": 10,\n    \"title\": \"fish\",\n    \"price\": \"3.0\",\n    \"description\": null,\n    \"created_at\": \"2016-03-12T04:25:56.810Z\",\n    \"updated_at\": \"2016-03-12T04:25:56.810Z\",\n    \"inventory_count\": 20,\n    \"image_url\": \"uploads/product/image/default.png\"\n  },\n  {\n    \"id\": 12,\n    \"city_id\": 10,\n    \"title\": \"fish\",\n    \"price\": \"3.0\",\n    \"description\": null,\n    \"created_at\": \"2016-03-12T04:25:56.922Z\",\n    \"updated_at\": \"2016-03-12T04:25:56.922Z\",\n    \"inventory_count\": 20,\n    \"image_url\": \"uploads/product/image/default.png\"\n  },\n  {\n    \"id\": 13,\n    \"city_id\": 10,\n    \"title\": \"fish\",\n    \"price\": \"3.0\",\n    \"description\": null,\n    \"created_at\": \"2016-03-12T04:25:57.031Z\",\n    \"updated_at\": \"2016-03-12T04:25:57.031Z\",\n    \"inventory_count\": 20,\n    \"image_url\": \"uploads/product/image/default.png\"\n  },\n  {\n    \"id\": 14,\n    \"city_id\": 10,\n    \"title\": \"fish\",\n    \"price\": \"3.0\",\n    \"description\": null,\n    \"created_at\": \"2016-03-12T04:25:57.478Z\",\n    \"updated_at\": \"2016-03-12T04:25:57.478Z\",\n    \"inventory_count\": 0,\n    \"image_url\": \"uploads/product/image/default.png\"\n  },\n  {\n    \"id\": 15,\n    \"city_id\": 10,\n    \"title\": \"fish\",\n    \"price\": \"3.0\",\n    \"description\": null,\n    \"created_at\": \"2016-03-12T04:25:57.618Z\",\n    \"updated_at\": \"2016-03-12T04:25:57.618Z\",\n    \"inventory_count\": 0,\n    \"image_url\": \"uploads/product/image/default.png\"\n  },\n  {\n    \"id\": 16,\n    \"city_id\": 10,\n    \"title\": \"fish\",\n    \"price\": \"3.0\",\n    \"description\": null,\n    \"created_at\": \"2016-03-12T04:25:57.721Z\",\n    \"updated_at\": \"2016-03-12T04:25:57.721Z\",\n    \"inventory_count\": 0,\n    \"image_url\": \"uploads/product/image/default.png\"\n  },\n  {\n    \"id\": 17,\n    \"city_id\": 11,\n    \"title\": \"fish\",\n    \"price\": \"3.0\",\n    \"description\": null,\n    \"created_at\": \"2016-03-12T04:25:58.308Z\",\n    \"updated_at\": \"2016-03-12T04:25:58.308Z\",\n    \"inventory_count\": 0,\n    \"image_url\": \"uploads/product/image/default.png\"\n  },\n  {\n    \"id\": 18,\n    \"city_id\": 12,\n    \"title\": \"fish\",\n    \"price\": \"3.0\",\n    \"description\": null,\n    \"created_at\": \"2016-03-12T04:25:58.530Z\",\n    \"updated_at\": \"2016-03-12T04:25:58.530Z\",\n    \"inventory_count\": 0,\n    \"image_url\": \"uploads/product/image/default.png\"\n  },\n  {\n    \"id\": 19,\n    \"city_id\": 13,\n    \"title\": \"fish\",\n    \"price\": \"3.0\",\n    \"description\": null,\n    \"created_at\": \"2016-03-12T04:25:58.775Z\",\n    \"updated_at\": \"2016-03-12T04:25:58.775Z\",\n    \"inventory_count\": 0,\n    \"image_url\": \"uploads/product/image/default.png\"\n  },\n  {\n    \"id\": 20,\n    \"city_id\": 14,\n    \"title\": \"fish\",\n    \"price\": \"3.0\",\n    \"description\": null,\n    \"created_at\": \"2016-03-12T04:25:58.997Z\",\n    \"updated_at\": \"2016-03-12T04:25:58.997Z\",\n    \"inventory_count\": 0,\n    \"image_url\": \"uploads/product/image/default.png\"\n  },\n  {\n    \"id\": 21,\n    \"city_id\": 15,\n    \"title\": \"fish\",\n    \"price\": \"3.0\",\n    \"description\": null,\n    \"created_at\": \"2016-03-12T04:25:59.219Z\",\n    \"updated_at\": \"2016-03-12T04:25:59.219Z\",\n    \"inventory_count\": 0,\n    \"image_url\": \"uploads/product/image/default.png\"\n  },\n  {\n    \"id\": 22,\n    \"city_id\": 16,\n    \"title\": \"fish\",\n    \"price\": \"3.0\",\n    \"description\": null,\n    \"created_at\": \"2016-03-12T04:25:59.441Z\",\n    \"updated_at\": \"2016-03-12T04:25:59.441Z\",\n    \"inventory_count\": 20,\n    \"image_url\": \"uploads/product/image/default.png\"\n  }\n]",
      "response_headers": {
        "X-Frame-Options": "SAMEORIGIN",
        "X-XSS-Protection": "1; mode=block",
        "X-Content-Type-Options": "nosniff",
        "Content-Type": "application/json; charset=utf-8",
        "ETag": "W/\"55ee186bfa17a403a03085e0343decb9\"",
        "Cache-Control": "max-age=0, private, must-revalidate",
        "X-Request-Id": "ceebf509-44bd-45bb-a1e1-64b2c6051dec",
        "X-Runtime": "0.019837",
        "Content-Length": "4814"
      },
      "response_content_type": "application/json; charset=utf-8",
      "curl": "curl \"http://localhost:3000/products\" -X GET \\\n\t-H \"Host: example.org\" \\\n\t-H \"Cookie: \""
    }
  ]
}